django_icons_bootstrap_icons/__init__.py
django_icons_bootstrap_icons-1.0.0.dist-info/METADATA
django_icons_bootstrap_icons-1.0.0.dist-info/WHEEL
django_icons_bootstrap_icons-1.0.0.dist-info/licenses/LICENSE
django_icons_bootstrap_icons-1.0.0.dist-info/RECORD
