Metadata-Version: 2.3
Name: django-icons-bootstrap-icons
Version: 1.0.0
Summary: Bootstrap Icons renderer for django-icons
Project-URL: Repository, https://github.com/pyrox0/django-icons-bootstrap-icons
Project-URL: Issues, https://github.com/pyrox0/django-icons-bootstrap-icons/issues
Project-URL: Changelog, https://github.com/pyrox0/django-icons-bootstrap-icons/releases
Author-email: Pyrox/dish <pyrox@pyrox.dev>
Maintainer-email: Pyrox/dish <pyrox@pyrox.dev>
License-File: LICENSE
Keywords: bootstrap,bootstrap-icons,django,django-icons,icons
Classifier: Development Status :: 5 - Production/Stable
Classifier: Framework :: Django
Classifier: Intended Audience :: Developers
Classifier: License :: OSI Approved :: MIT License
Classifier: Operating System :: OS Independent
Classifier: Programming Language :: Python
Classifier: Programming Language :: Python :: 3
Classifier: Programming Language :: Python :: 3 :: Only
Classifier: Programming Language :: Python :: 3.10
Classifier: Programming Language :: Python :: 3.11
Classifier: Programming Language :: Python :: 3.12
Classifier: Programming Language :: Python :: 3.13
Classifier: Programming Language :: Python :: 3.14
Classifier: Topic :: Software Development :: Libraries
Classifier: Topic :: Software Development :: Libraries :: Python Modules
Requires-Python: >=3.10
Requires-Dist: django-icons>=24.3
